poseigen_oyster/__init__.py
poseigen_oyster/analysis.py
poseigen_oyster/model.py
poseigen_oyster-0.0.4.dist-info/LICENSE.txt
poseigen_oyster-0.0.4.dist-info/METADATA
poseigen_oyster-0.0.4.dist-info/WHEEL
poseigen_oyster-0.0.4.dist-info/RECORD
